xesmf/__init__.py
xesmf/_version.py
xesmf/backend.py
xesmf/data.py
xesmf/frontend.py
xesmf/smm.py
xesmf/util.py
xesmf/tests/__init__.py
xesmf/tests/conftest.py
xesmf/tests/test_backend.py
xesmf/tests/test_frontend.py
xesmf/tests/test_oceanmodels.py
xesmf/tests/test_smm.py
xesmf/tests/test_util.py
xesmf-0.8.9.dist-info/licenses/LICENSE
xesmf-0.8.9.dist-info/METADATA
xesmf-0.8.9.dist-info/WHEEL
xesmf-0.8.9.dist-info/top_level.txt
xesmf-0.8.9.dist-info/RECORD
