Metadata-Version: 2.4
Name: xesmf
Version: 0.8.9
Summary: Universal Regridder for Geospatial Data
Author-email: Jiawei Zhuang <jiaweizhuang@g.harvard.edu>
License: MIT
Project-URL: documentation, https://xesmf.readthedocs.io/en/latest/
Project-URL: homepage, https://github.com/pangeo-data/xESMF
Project-URL: repository, https://github.com/pangeo-data/xESMF
Classifier: Development Status :: 4 - Beta
Classifier: Intended Audience :: Science/Research
Classifier: License :: OSI Approved :: MIT License
Classifier: Operating System :: OS Independent
Classifier: Programming Language :: Python
Classifier: Programming Language :: Python :: 3 :: Only
Classifier: Programming Language :: Python :: 3.8
Classifier: Programming Language :: Python :: 3.9
Classifier: Programming Language :: Python :: 3.10
Classifier: Programming Language :: Python :: 3.11
Classifier: Programming Language :: Python :: 3.12
Classifier: Programming Language :: Python :: 3.13
Classifier: Topic :: Scientific/Engineering
Requires-Python: >=3.8
License-File: LICENSE
Requires-Dist: cf-xarray>=0.5.1
Requires-Dist: numba>=0.55.2
Requires-Dist: numpy>=1.16
Requires-Dist: shapely
Requires-Dist: sparse>=0.8.0
Requires-Dist: xarray>=0.16.2
Dynamic: license-file
